{
  "baseButton": {
    "primaryBackgroundColor": {
      "value": "{color.background.interactive.action.primary.base}",
      "type": "color"
    },
    "primaryHoverBackgroundColor": {
      "value": "{color.background.interactive.action.primary.hover}",
      "type": "color"
    },
    "primaryActiveBackgroundColor": {
      "value": "{color.background.interactive.action.primary.active}",
      "type": "color"
    },
    "primaryDisabledBackgroundColor": {
      "value": "{color.background.interactive.action.primary.disabled}",
      "type": "color"
    },
    "primaryBorderColor": {
      "value": "{color.stroke.interactive.action.primary.base}",
      "type": "color"
    },
    "primaryDisabledBorderColor": {
      "value": "{color.stroke.interactive.action.primary.disabled}",
      "type": "color"
    },
    "primaryBaseTextColor": {
      "value": "{color.text.interactive.action.primary.base}",
      "type": "color"
    },
    "secondaryBackgroundColor": {
      "value": "{color.background.interactive.action.secondary.base}",
      "type": "color"
    },
    "secondaryHoverBackgroundColor": {
      "value": "{color.background.interactive.action.secondary.hover}",
      "type": "color"
    },
    "secondaryActiveBackgroundColor": {
      "value": "{color.background.interactive.action.secondary.active}",
      "type": "color"
    },
    "secondaryDisabledBackgroundColor": {
      "value": "{color.background.interactive.action.secondary.disabled}",
      "type": "color"
    },
    "secondaryBorderColor": {
      "value": "{color.stroke.interactive.action.secondary.base}",
      "type": "color"
    },
    "secondaryTextColor": {
      "value": "{color.text.interactive.action.secondary.base}",
      "type": "color"
    },
    "secondaryDisabledTextColor": {
      "value": "{color.text.interactive.action.secondary.disabled}",
      "type": "color"
    },
    "secondaryDisabledBorderColor": {
      "value": "{color.stroke.interactive.action.secondary.disabled}",
      "type": "color"
    },
    "successBackgroundColor": {
      "value": "{color.background.interactive.action.success.base}",
      "type": "color"
    },
    "successHoverBackgroundColor": {
      "value": "{color.background.interactive.action.success.hover}",
      "type": "color"
    },
    "successActiveBackgroundColor": {
      "value": "{color.background.interactive.action.success.active}",
      "type": "color"
    },
    "successDisabledBackgroundColor": {
      "value": "{color.background.interactive.action.success.disabled}",
      "type": "color"
    },
    "successBorderColor": {
      "value": "{color.stroke.interactive.action.success.base}",
      "type": "color"
    },
    "successDisabledBorderColor": {
      "value": "{color.stroke.interactive.action.success.disabled}",
      "type": "color"
    },
    "successTextColor": {
      "value": "{color.text.interactive.action.status.base}",
      "type": "color"
    },
    "destructiveBackgroundColor": {
      "value": "{color.background.interactive.action.destructive.base}",
      "type": "color"
    },
    "destructiveHoverBackgroundColor": {
      "value": "{color.background.interactive.action.destructive.hover}",
      "type": "color"
    },
    "destructiveActiveBackgroundColor": {
      "value": "{color.background.interactive.action.destructive.active}",
      "type": "color"
    },
    "destructiveDisabledBackgroundColor": {
      "value": "{color.background.interactive.action.destructive.disabled}",
      "type": "color"
    },
    "destructiveBorderColor": {
      "value": "{color.stroke.interactive.action.destructive.base}",
      "type": "color"
    },
    "destructiveDisabledBorderColor": {
      "value": "{color.stroke.interactive.action.destructive.disabled}",
      "type": "color"
    },
    "destructiveTextColor": {
      "value": "{color.text.interactive.action.status.base}",
      "type": "color"
    },
    "aiBackgroundBottomGradientColor": {
      "value": "{color.background.interactive.action.ai.bottomGradient.base}",
      "type": "color"
    },
    "aiHoverBackgroundBottomGradientColor": {
      "value": "{color.background.interactive.action.ai.bottomGradient.hover}",
      "type": "color"
    },
    "aiActiveBackgroundBottomGradientColor": {
      "value": "{color.background.interactive.action.ai.bottomGradient.active}",
      "type": "color"
    },
    "aiDisabledBackgroundBottomGradientColor": {
      "value": "{color.background.interactive.action.ai.bottomGradient.disabled}",
      "type": "color"
    },
    "aiBackgroundTopGradientColor": {
      "value": "{color.background.interactive.action.ai.topGradient.base}",
      "type": "color"
    },
    "aiHoverBackgroundTopGradientColor": {
      "value": "{color.background.interactive.action.ai.topGradient.hover}",
      "type": "color"
    },
    "aiActiveBackgroundTopGradientColor": {
      "value": "{color.background.interactive.action.ai.topGradient.active}",
      "type": "color"
    },
    "aiDisabledBackgroundTopGradientColor": {
      "value": "{color.background.interactive.action.ai.topGradient.disabled}",
      "type": "color"
    },
    "aiBorderTopGradientColor": {
      "value": "{color.stroke.interactive.action.ai.topGradient.base}",
      "type": "color"
    },
    "aiDisabledBorderTopGradientColor": {
      "value": "{color.stroke.interactive.action.ai.topGradient.disabled}",
      "type": "color"
    },
    "aiBorderBottomGradientColor": {
      "value": "{color.stroke.interactive.action.ai.bottomGradient.base}",
      "type": "color"
    },
    "aiDisabledBorderBottomGradientColor": {
      "value": "{color.stroke.interactive.action.ai.bottomGradient.disabled}",
      "type": "color"
    },
    "aiTextColor": {
      "value": "{color.text.interactive.action.ai.base}",
      "type": "color"
    },
    "aiSecondaryBackgroundColor": {
      "value": "{color.background.interactive.action.aiSecondary.base}",
      "type": "color"
    },
    "aiSecondaryTextTopGradientColor": {
      "value": "{color.text.interactive.action.aiSecondary.topGradient.base}",
      "type": "color"
    },
    "aiSecondaryTextBottomGradientColor": {
      "value": "{color.text.interactive.action.aiSecondary.bottomGradient.base}",
      "type": "color"
    },
    "aiSecondaryHoverBackgroundTopGradientColor": {
      "value": "{color.background.interactive.action.aiSecondary.hover.topGradient}",
      "type": "color"
    },
    "aiSecondaryHoverBackgroundBottomGradientColor": {
      "value": "{color.background.interactive.action.aiSecondary.hover.bottomGradient}",
      "type": "color"
    },
    "primaryHoverTextColor": {
      "value": "{color.text.interactive.action.primary.hover}",
      "type": "color"
    },
    "primaryActiveTextColor": {
      "value": "{color.text.interactive.action.primary.active}",
      "type": "color"
    },
    "primaryDisabledTextColor": {
      "value": "{color.text.interactive.action.primary.disabled}",
      "type": "color"
    },
    "primaryOnColorBackgroundColor": {
      "value": "{color.background.interactive.action.primaryOnColor.base}",
      "type": "color"
    },
    "primaryOnColorHoverBackgroundColor": {
      "value": "{color.background.interactive.action.primaryOnColor.hover}",
      "type": "color"
    },
    "primaryOnColorActiveBackgroundColor": {
      "value": "{color.background.interactive.action.primaryOnColor.active}",
      "type": "color"
    },
    "primaryOnColorDisabledBackgroundColor": {
      "value": "{color.background.interactive.action.primaryOnColor.disabled}",
      "type": "color"
    },
    "primaryOnColorBorderColor": {
      "value": "{color.stroke.interactive.action.primaryOnColor.base}",
      "type": "color"
    },
    "primaryOnColorTextColor": {
      "value": "{color.text.interactive.action.primaryOnColor.base}",
      "type": "color"
    },
    "primaryOnColorDisabledTextColor": {
      "value": "{color.text.interactive.action.primaryOnColor.disabled}",
      "type": "color"
    },
    "heightSm": {
      "value": "{size.interactive.height.sm}",
      "type": "sizing"
    },
    "heightMd": {
      "value": "{size.interactive.height.md}",
      "type": "sizing"
    },
    "heightLg": {
      "value": "{size.interactive.height.lg}",
      "type": "sizing"
    },
    "paddingHorizontalMd": {
      "value": "{spacing.padding.interactive.horizontal.md}",
      "type": "spacing"
    },
    "paddingHorizontalSm": {
      "value": "{spacing.padding.interactive.horizontal.sm}",
      "type": "spacing"
    },
    "paddingHorizontalLg": {
      "value": "{spacing.padding.interactive.horizontal.lg}",
      "type": "spacing"
    },
    "borderRadiusBase": {
      "value": "{borderRadius.interactive.base}",
      "type": "borderRadius"
    },
    "borderWidth": {
      "value": "{borderWidth.interactive.base}",
      "type": "borderWidth"
    },
    "fontFamily": {
      "value": "{fontFamily.base}",
      "type": "fontFamilies"
    },
    "fontWeight": {
      "value": "{fontWeight.body.base}",
      "type": "fontWeights"
    },
    "gapButtonContentSm": {
      "value": "{spacing.spaceXs}",
      "type": "spacing"
    },
    "gapButtonContentMd": {
      "value": "{spacing.spaceSm}",
      "type": "spacing"
    },
    "gapButtonContentLg": {
      "value": "{spacing.spaceMd}",
      "type": "spacing"
    },
    "fontSizeSm": {
      "value": "{fontSize.textSm}",
      "type": "fontSizes"
    },
    "fontSizeMd": {
      "value": "{fontSize.textBase}",
      "type": "fontSizes"
    },
    "fontSizeLg": {
      "value": "1.375rem",
      "type": "fontSizes"
    },
    "lineHeightSm": {
      "value": "{lineHeight.standalone.textSm}",
      "type": "lineHeights"
    },
    "lineHeightMd": {
      "value": "{lineHeight.standalone.textBase}",
      "type": "lineHeights"
    },
    "lineHeightLg": {
      "value": "1.375rem",
      "type": "lineHeights"
    },
    "primaryHoverBorderColor": {
      "value": "{color.stroke.interactive.action.primary.hover}",
      "type": "color"
    },
    "primaryActiveBorderColor": {
      "value": "{color.stroke.interactive.action.primary.active}",
      "type": "color"
    },
    "successHoverBorderColor": {
      "value": "{color.stroke.interactive.action.success.hover}",
      "type": "color"
    },
    "successActiveBorderColor": {
      "value": "{color.stroke.interactive.action.success.active}",
      "type": "color"
    },
    "destructiveHoverBorderColor": {
      "value": "{color.stroke.interactive.action.destructive.hover}",
      "type": "color"
    },
    "destructiveActiveBorderColor": {
      "value": "{color.stroke.interactive.action.destructive.active}",
      "type": "color"
    },
    "primaryOnColorHoverBorderColor": {
      "value": "{color.stroke.interactive.action.primaryOnColor.hover}",
      "type": "color"
    },
    "primaryOnColorActiveBorderColor": {
      "value": "{color.stroke.interactive.action.primaryOnColor.active}",
      "type": "color"
    },
    "primaryOnColorDisabledBorderColor": {
      "value": "{color.stroke.interactive.action.primaryOnColor.disabled}",
      "type": "color"
    },
    "aiSecondaryDisabledTextTopGradientColor": {
      "value": "{color.text.interactive.action.aiSecondary.topGradient.disabled}",
      "type": "color"
    },
    "aiSecondaryDisabledTextBottomGradientColor": {
      "value": "{color.text.interactive.action.aiSecondary.bottomGradient.disabled}",
      "type": "color"
    },
    "destructiveDisabledTextColor": {
      "value": "{color.text.interactive.action.status.disabled}",
      "type": "color"
    },
    "successDisabledTextColor": {
      "value": "{color.text.interactive.action.status.disabled}",
      "type": "color"
    },
    "aiDisabledTextColor": {
      "value": "{color.text.interactive.action.ai.disabled}",
      "type": "color"
    },
    "aiSecondaryDisabledBackgroundColor": {
      "value": "{color.background.interactive.action.aiSecondary.disabled}",
      "type": "color"
    },
    "secondaryHoverBorderColor": {
      "value": "{color.stroke.interactive.action.secondary.hover}",
      "type": "color"
    },
    "secondaryActiveBorderColor": {
      "value": "{color.stroke.interactive.action.secondary.active}",
      "type": "color"
    },
    "aiSecondaryActiveBackgroundTopGradientColor": {
      "value": "{color.background.interactive.action.aiSecondary.active.topGradient}",
      "type": "color"
    },
    "aiSecondaryActiveBackgroundBottomGradientColor": {
      "value": "{color.background.interactive.action.aiSecondary.active.bottomGradient}",
      "type": "color"
    },
    "tertiaryHoverBackgroundColor": {
      "value": "{color.background.interactive.action.tertiary.hover}",
      "type": "color"
    },
    "tertiaryActiveBackgroundColor": {
      "value": "{color.background.interactive.action.tertiary.active}",
      "type": "color"
    },
    "tertiaryBorderColor": {
      "value": "{color.stroke.interactive.action.tertiary.base}",
      "type": "color"
    },
    "tertiaryHoverBorderColor": {
      "value": "{color.stroke.interactive.action.tertiary.hover}",
      "type": "color"
    },
    "tertiaryActiveBorderColor": {
      "value": "{color.stroke.interactive.action.tertiary.active}",
      "type": "color"
    },
    "tertiaryDisabledBorderColor": {
      "value": "{color.stroke.interactive.action.tertiary.disabled}",
      "type": "color"
    },
    "tertiaryTextColor": {
      "value": "{color.text.interactive.action.tertiary.base}",
      "type": "color"
    },
    "tertiaryDisabledTextColor": {
      "value": "{color.text.interactive.action.tertiary.disabled}",
      "type": "color"
    },
    "successSecondaryHoverBackgroundColor": {
      "value": "{color.background.interactive.action.success.secondary.hover}",
      "type": "color"
    },
    "successSecondaryActiveBackgroundColor": {
      "value": "{color.background.interactive.action.success.secondary.active}",
      "type": "color"
    },
    "successSecondaryTextColor": {
      "value": "{color.text.interactive.action.successSecondary.base}",
      "type": "color"
    },
    "successSecondaryDisabledTextColor": {
      "value": "{color.text.interactive.action.successSecondary.disabled}",
      "type": "color"
    },
    "successSecondaryBorderColor": {
      "value": "{color.stroke.interactive.action.success.secondary.base}",
      "type": "color"
    },
    "successSecondaryHoverBorderColor": {
      "value": "{color.stroke.interactive.action.success.secondary.hover}",
      "type": "color"
    },
    "successSecondaryActiveBorderColor": {
      "value": "{color.stroke.interactive.action.success.secondary.active}",
      "type": "color"
    },
    "successSecondaryDisabledBorderColor": {
      "value": "{color.stroke.interactive.action.success.secondary.disabled}",
      "type": "color"
    },
    "destructiveSecondaryHoverBackgroundColor": {
      "value": "{color.background.interactive.action.destructive.secondary.hover}",
      "type": "color"
    },
    "destructiveSecondaryActiveBackgroundColor": {
      "value": "{color.background.interactive.action.destructive.secondary.active}",
      "type": "color"
    },
    "destructiveSecondaryTextColor": {
      "value": "{color.text.interactive.action.destructiveSecondary.base}",
      "type": "color"
    },
    "destructiveSecondaryDisabledTextColor": {
      "value": "{color.text.interactive.action.destructiveSecondary.disabled}",
      "type": "color"
    },
    "destructiveSecondaryBorderColor": {
      "value": "{color.stroke.interactive.action.destructive.secondary.base}",
      "type": "color"
    },
    "destructiveSecondaryHoverBorderColor": {
      "value": "{color.stroke.interactive.action.destructive.secondary.hover}",
      "type": "color"
    },
    "destructiveSecondaryActiveBorderColor": {
      "value": "{color.stroke.interactive.action.destructive.secondary.active}",
      "type": "color"
    },
    "destructiveSecondaryDisabledBorderColor": {
      "value": "{color.stroke.interactive.action.destructive.secondary.disabled}",
      "type": "color"
    },
    "ghostOncolorHoverBackgroundColor": {
      "value": "{color.background.interactive.action.ghost.onColor.hover}",
      "type": "color"
    },
    "ghostOncolorActiveBackgroundColor": {
      "value": "{color.background.interactive.action.ghost.onColor.hover}",
      "type": "color"
    },
    "borderRadiusSm": {
      "value": "{borderRadius.sm}",
      "type": "borderRadius"
    },
    "heightXxs": {
      "value": "{size.interactive.height.xxs}",
      "type": "sizing"
    },
    "heightXs": {
      "value": "{size.interactive.height.xs}",
      "type": "sizing"
    },
    "opacityBase": {
      "value": "{opacity.base}",
      "type": "opacity"
    },
    "opacityDisabled": {
      "value": "{opacity.disabled}",
      "type": "opacity"
    }
  }
}