{
  "icon": {
    "sizeXs": {
      "value": "0.75rem",
      "type": "sizing"
    },
    "sizeSm": {
      "value": "1rem",
      "type": "sizing"
    },
    "sizeMd": {
      "value": "1.25rem",
      "type": "sizing"
    },
    "sizeLg": {
      "value": "1.5rem",
      "type": "sizing"
    },
    "sizeXl": {
      "value": "2rem",
      "type": "sizing"
    },
    "size2xl": {
      "value": "2.25rem",
      "type": "sizing"
    },
    "strokeWidthXs": {
      "value": "0.0625rem",
      "type": "borderWidth"
    },
    "strokeWidthSm": {
      "value": "0.078125rem",
      "type": "borderWidth"
    },
    "strokeWidthMd": {
      "value": "0.09375rem",
      "type": "borderWidth"
    },
    "strokeWidthLg": {
      "value": "0.125rem",
      "type": "borderWidth"
    },
    "strokeWidthXl": {
      "value": "0.15625rem",
      "type": "borderWidth"
    },
    "strokeWidth2xl": {
      "value": "0.1875rem",
      "type": "borderWidth"
    },
    "baseColor": {
      "value": "{color.icon.base}",
      "type": "color"
    },
    "disabledColor": {
      "value": "{color.icon.interactive.disabled.base}",
      "type": "color"
    },
    "disabledOnColor": {
      "value": "{color.icon.interactive.disabled.onColor}",
      "type": "color"
    },
    "primaryBaseColor": {
      "value": "{color.icon.interactive.navigation.primary.base}",
      "type": "color"
    },
    "primaryHoverColor": {
      "value": "{color.icon.interactive.navigation.primary.hover}",
      "type": "color"
    },
    "destructiveColor": {
      "value": "{color.icon.interactive.action.destructive.base}",
      "type": "color"
    },
    "destructiveHoverColor": {
      "value": "{color.icon.interactive.action.destructive.hover}",
      "type": "color"
    },
    "mutedColor": {
      "value": "{color.icon.muted}",
      "type": "color"
    },
    "successColor": {
      "value": "{color.icon.success}",
      "type": "color"
    },
    "errorColor": {
      "value": "{color.icon.error}",
      "type": "color"
    },
    "warningColor": {
      "value": "{color.icon.warning}",
      "type": "color"
    },
    "infoColor": {
      "value": "{color.icon.info}",
      "type": "color"
    },
    "onColor": {
      "value": "{color.icon.onColor}",
      "type": "color"
    },
    "accent1Color": {
      "value": "{color.icon.accent.color1}",
      "type": "color"
    },
    "accent2Color": {
      "value": "{color.icon.accent.color2}",
      "type": "color"
    },
    "accent3Color": {
      "value": "{color.icon.accent.color3}",
      "type": "color"
    },
    "accent4Color": {
      "value": "{color.icon.accent.color4}",
      "type": "color"
    },
    "accent5Color": {
      "value": "{color.icon.accent.color5}",
      "type": "color"
    },
    "accent6Color": {
      "value": "{color.icon.accent.color6}",
      "type": "color"
    }
  }
}