{"comment":"/**\n * ---\n * category: utilities/PropTypes\n * ---\n * Verify that a prop cannot be given if one or more other props are also\n * given.\n *\n * ```js-code\n *  import { xor } from '@instructure/ui-prop-types'\n *\n *  class Foo extends Component {\n *    static propTypes = {\n *      decimalPrecision: xor(PropTypes.number, 'significantDigits'),\n *      significantDigits: xor(PropTypes.number, 'decimalPrecision')\n *    }\n *  ...\n * ```\n *\n * This will throw an error if both the `decimalPrecision` and\n * `significantDigits` props are provided.\n * @module xor\n * @param {function} propType - validates the prop type. Returns null if valid, error otherwise\n * @param {...string} otherPropNames - reject if any of these other props are also given\n * @returns {function} A function that returns Error if any of the other props\n * are also given, null otherwise\n */","meta":{"filename":"8p1amoj1kjhedeoodyn28k.js","lineno":1,"columnno":0,"path":"/tmp","code":{}},"description":"Verify that a prop cannot be given if one or more other props are also\ngiven.\n\n```js-code\n import { xor } from '@instructure/ui-prop-types'\n\n class Foo extends Component {\n   static propTypes = {\n     decimalPrecision: xor(PropTypes.number, 'significantDigits'),\n     significantDigits: xor(PropTypes.number, 'decimalPrecision')\n   }\n ...\n```\n\nThis will throw an error if both the `decimalPrecision` and\n`significantDigits` props are provided.","kind":"module","name":"xor","params":[{"type":{"names":["function"]},"description":"validates the prop type. Returns null if valid, error otherwise","name":"propType"},{"type":{"names":["string"]},"variable":true,"description":"reject if any of these other props are also given","name":"otherPropNames"}],"returns":[{"type":{"names":["function"]},"description":"A function that returns Error if any of the other props\nare also given, null otherwise"}],"longname":"module:xor","undocumented":false,"category":"utilities/PropTypes","relativePath":"packages/ui-prop-types/src/xor.ts","extension":".ts","srcPath":"packages/ui-prop-types/src/xor.ts","srcUrl":"https://github.com/instructure/instructure-ui/tree/master/packages/ui-prop-types/src/xor.ts","packageName":"@instructure/ui-prop-types","requirePath":"@instructure/ui-prop-types/lib/xor","requireStr":"require('/home/runner/work/instructure-ui/instructure-ui/packages/ui-prop-types/src/xor.ts').default","esPath":"@instructure/ui-prop-types/es/xor","themePath":"packages/ui-prop-types/src/xor.ts","themeUrl":"https://github.com/instructure/instructure-ui/tree/master/packages/ui-prop-types/src/xor.ts","id":"xor","title":"xor"}