{"description":"@module ScreenReaderContent\nThe ScreenReaderContent component renders content that is accessible to\nscreen readers, but is not visible.\n\n```js\n---\ntype: example\n---\n<ScreenReaderContent>\n  This content is not visible.\n</ScreenReaderContent>\n```\n","displayName":"ScreenReaderContent","methods":[{"name":"handleRef","docblock":null,"modifiers":[],"params":[{"name":"el","optional":false,"type":{"name":"union","raw":"Element | null","elements":[{"name":"Element"},{"name":"null"}]}}],"returns":null}],"props":{"as":{"required":false,"tsType":{"name":"union","raw":"keyof JSX.IntrinsicElements | ComponentType<P>","elements":[{"name":"JSX.IntrinsicElements"},{"name":"ComponentType","elements":[{"name":"P"}],"raw":"ComponentType<P>"}]},"description":"the element type to render as","defaultValue":{"value":"'span'","computed":false}},"children":{"required":false,"tsType":{"name":"ReactNode"},"description":"content meant for screen readers only","defaultValue":{"value":"null","computed":false}},"elementRef":{"required":false,"tsType":{"name":"signature","type":"function","raw":"(element: Element | null) => void","signature":{"arguments":[{"type":{"name":"union","raw":"Element | null","elements":[{"name":"Element"},{"name":"null"}]},"name":"element"}],"return":{"name":"void"}}},"description":"provides a reference to the underlying html root element"},"dir":{"required":false,"tsType":{"name":"union","raw":"'ltr' | 'rtl'","elements":[{"name":"literal","value":"'ltr'"},{"name":"literal","value":"'rtl'"}]},"description":""}},"category":"utilities/a11y","relativePath":"packages/ui-a11y-content/src/ScreenReaderContent/index.tsx","extension":".tsx","srcPath":"packages/ui-a11y-content/src/ScreenReaderContent/index.tsx","srcUrl":"https://github.com/instructure/instructure-ui/tree/master/packages/ui-a11y-content/src/ScreenReaderContent/index.tsx","packageName":"@instructure/ui-a11y-content","requirePath":"@instructure/ui-a11y-content/lib/ScreenReaderContent/index","requireStr":"require('/home/runner/work/instructure-ui/instructure-ui/packages/ui-a11y-content/src/ScreenReaderContent/index.tsx').default","esPath":"@instructure/ui-a11y-content/es/ScreenReaderContent/index","id":"ScreenReaderContent","title":"ScreenReaderContent"}